global_query_strings/__init__.py
global_query_strings/middleware.py
global_query_strings/utils.py
django_global_query_strings-0.4.0.dist-info/LICENSE
django_global_query_strings-0.4.0.dist-info/METADATA
django_global_query_strings-0.4.0.dist-info/WHEEL
django_global_query_strings-0.4.0.dist-info/top_level.txt
django_global_query_strings-0.4.0.dist-info/RECORD
